_version.py
binda.py
example/PHOTO.JPG
example/PHOTO_EDITED.JPG
example/example.ipynb
example/usage.ipynb
example/img/repeating_structure.png
example/img/repeating_structure_changed.png
example/img/single_structure.png
binda-1.0.22.dist-info/METADATA
binda-1.0.22.dist-info/WHEEL
binda-1.0.22.dist-info/entry_points.txt
binda-1.0.22.dist-info/licenses/LICENSE
binda-1.0.22.dist-info/RECORD
