Metadata-Version: 2.1
Name: binda
Version: 1.0.22
Summary: Read and write binary data using Pandas
Project-URL: Homepage, https://github.com/jamiecash/binda
Project-URL: Bug Tracker, https://github.com/jamiecash/binda/issues
Project-URL: Documentation, https://jamiecash.github.io/binda/binda.html
Author-email: Jamie Cash <jlcash@gmail.com>
License: MIT License
License-File: LICENSE
Keywords: analytics,binary,data,hex,hexadecimal,pandas
Classifier: Development Status :: 5 - Production/Stable
Classifier: Intended Audience :: Developers
Classifier: License :: OSI Approved :: MIT License
Classifier: Operating System :: OS Independent
Classifier: Programming Language :: Python :: 3
Classifier: Programming Language :: Python :: 3 :: Only
Classifier: Programming Language :: Python :: 3.6
Classifier: Programming Language :: Python :: 3.7
Classifier: Programming Language :: Python :: 3.8
Classifier: Programming Language :: Python :: 3.9
Classifier: Programming Language :: Python :: 3.10
Classifier: Programming Language :: Python :: 3.11
Classifier: Topic :: Software Development :: Build Tools
Requires-Python: >=3.6
Requires-Dist: build
Requires-Dist: flake8
Requires-Dist: hatch-vcs
Requires-Dist: hatchling
Requires-Dist: numpy
Requires-Dist: pandas
Requires-Dist: pdoc
Requires-Dist: pytest
Requires-Dist: twine
